.gitignore
MANIFEST.in
README.rst
bootstrap.py
buildout.cfg
setup.py
validation-files.yaml
validation-options.yaml
docs/HISTORY.txt
docs/LICENSE.GPL
docs/LICENSE.txt
silvuple/__init__.py
silvuple/i18n.py
silvuple/interfaces.py
silvuple/negotiator.py
silvuple/plone3.py
silvuple/settings.py
silvuple/views.py
silvuple.egg-info/PKG-INFO
silvuple.egg-info/SOURCES.txt
silvuple.egg-info/dependency_links.txt
silvuple.egg-info/entry_points.txt
silvuple.egg-info/requires.txt
silvuple.egg-info/top_level.txt