Metadata-Version: 1.1
Name: silvuple
Version: 1.2
Summary: Translation manager for Plone / LinguaPlone websites
Home-page: http://opensourcehacker.com
Author: Mikko Ohtamaa
Author-email: mikko@opensourcehacker.com
License: GPL2
Platform: UNKNOWN
Classifier: Framework :: Plone
Classifier: Programming Language :: Python
